Metadata-Version: 2.4
Name: python-secp256k1-cardano
Version: 0.2.4
Summary: Ctypes Python3 FFI bindings for libsecp256k1 at commit hash ac83be33
Author-email: scg <scgbckbone@proton.me>
License-Expression: MIT
Project-URL: Homepage, https://github.com/ImperatorLang/python-secp256k1
Keywords: bitcoin,secp256k1,ecdsa,schnorr
Classifier: Programming Language :: Python :: 3.9
Classifier: Programming Language :: Python :: 3.10
Classifier: Programming Language :: Python :: 3.11
Classifier: Programming Language :: Python :: 3.12
Classifier: Programming Language :: Python :: 3.13
Requires-Python: >=3.6
License-File: LICENSE
Provides-Extra: typing-extensions
Requires-Dist: typing_extensions>=3.6; extra == "typing-extensions"
Dynamic: license-file
